sparse_numeric_table/__init__.py
sparse_numeric_table/_base.py
sparse_numeric_table/_file_io.py
sparse_numeric_table/_sparse_numeric_table.py
sparse_numeric_table/logic.py
sparse_numeric_table/testing.py
sparse_numeric_table/validating.py
sparse_numeric_table/version.py
sparse_numeric_table_sebastian_achim_mueller-1.2.11.dist-info/licenses/LICENSE
sparse_numeric_table_sebastian_achim_mueller-1.2.11.dist-info/METADATA
sparse_numeric_table_sebastian_achim_mueller-1.2.11.dist-info/WHEEL
sparse_numeric_table_sebastian_achim_mueller-1.2.11.dist-info/top_level.txt
sparse_numeric_table_sebastian_achim_mueller-1.2.11.dist-info/RECORD
