Metadata-Version: 2.4
Name: sparse_numeric_table_sebastian-achim-mueller
Version: 1.2.11
Summary: Read, write, and query sparse tables
Home-page: https://github.com/cherenkov-plenoscope/sparse_numeric_table
Author: Sebastian Achim Mueller
Author-email: sebastian-achim.mueller@mpi-hd.mpg.de
Classifier: Programming Language :: Python :: 3
Classifier: License :: OSI Approved :: MIT License
Classifier: Operating System :: OS Independent
Classifier: Natural Language :: English
Classifier: Intended Audience :: Science/Research
Classifier: Topic :: Scientific/Engineering :: Mathematics
License-File: LICENSE
Requires-Dist: numpy
Requires-Dist: pandas
Requires-Dist: dynamicsizerecarray>=0.1.0
Dynamic: author
Dynamic: author-email
Dynamic: classifier
Dynamic: description
Dynamic: description-content-type
Dynamic: home-page
Dynamic: license-file
Dynamic: requires-dist
Dynamic: summary
